tests/__init__.py
tests/execute_random_tests.py
tests/test_addchar.py
tests/test_changetype.py
tests/test_characterreport.py
tests/test_copypaste.py
tests/test_cut.py
tests/test_delete.py
tests/test_ismodified.py
tests/test_join_elems.py
tests/test_locationreport.py
tests/test_locations.py
tests/test_movement.py
tests/test_myimport.py
tests/test_pagelist.py
tests/test_renderscreenplay.py
tests/test_scenereport.py
tests/test_scriptreport.py
tests/test_util.py
tests/test_validate.py
tests/u.py
trelby/__init__.py
trelby/autocompletion.py
trelby/autocompletiondlg.py
trelby/autocompletiontype.py
trelby/cfgdlg.py
trelby/characterreport.py
trelby/charmapdlg.py
trelby/commandsdlg.py
trelby/config.py
trelby/dialoguechart.py
trelby/dict_en.dat.gz
trelby/error.py
trelby/fileformat.txt
trelby/finddlg.py
trelby/fontinfo.py
trelby/globaldata.py
trelby/gutil.py
trelby/headers.py
trelby/headersdlg.py
trelby/ids.py
trelby/importdlg.py
trelby/indent.py
trelby/line.py
trelby/locationreport.py
trelby/locations.py
trelby/locationsdlg.py
trelby/manual.html
trelby/misc.py
trelby/myimport.py
trelby/mypager.py
trelby/mypickle.py
trelby/namearray.py
trelby/names.txt.gz
trelby/namesdlg.py
trelby/opts.py
trelby/pagelist.py
trelby/pdf.py
trelby/pml.py
trelby/reports.py
trelby/sample.trelby
trelby/scenereport.py
trelby/screenplay.py
trelby/scriptreport.py
trelby/spellcheck.py
trelby/spellcheckcfgdlg.py
trelby/spellcheckdlg.py
trelby/splash.py
trelby/titles.py
trelby/titlesdlg.py
trelby/titlespreview.py
trelby/translations.py
trelby/trelby.1.gz
trelby/trelby.py
trelby/trelbyctrl.py
trelby/trelbyframe.py
trelby/trelbypanel.py
trelby/truetype.py
trelby/undo.py
trelby/util.py
trelby/viewmode.py
trelby/watermarkdlg.py
trelby/configpages/aboutpanel.py
trelby/configpages/colorspanel.py
trelby/configpages/displaypanel.py
trelby/configpages/elementsglobalpanel.py
trelby/configpages/elementspanel.py
trelby/configpages/formattingpanel.py
trelby/configpages/globalaboutpanel.py
trelby-2.4.16.2.dist-info/licenses/LICENSE
trelby-2.4.16.2.dist-info/METADATA
trelby-2.4.16.2.dist-info/WHEEL
trelby-2.4.16.2.dist-info/entry_points.txt
trelby-2.4.16.2.dist-info/top_level.txt
trelby-2.4.16.2.dist-info/RECORD
