Metadata-Version: 2.4
Name: trelby
Version: 2.4.16.2
Summary: Free, multiplatform, feature-rich screenwriting program
Home-page: https://www.trelby.org
Author: Osku Salerma
Author-email: osku.salerma@gmail.com
License: GPL-3.0-or-later
Classifier: Programming Language :: Python :: 3
Classifier: Operating System :: OS Independent
Requires-Python: >=3.9
License-File: LICENSE
Requires-Dist: wxPython
Requires-Dist: lxml
Requires-Dist: reportlab
Dynamic: license-file
